phynteny_transformer-0.1.2.data/scripts/phynteny_transformer
phynteny_transformer-0.1.2.dist-info/licenses/LICENSE
phynteny_utils/__init__.py
phynteny_utils/integer_category.pkl
phynteny_utils/phrog_annot_v4.tsv
src/__init__.py
src/advanced_argparse.py
src/format_data.py
src/install_models.py
src/integer_category.pkl
src/merge_pkl.py
src/model_onehot.py
src/predictor.py
src/phrog_annotation_info/phrog_annot_v4.tsv
phynteny_transformer-0.1.2.dist-info/METADATA
phynteny_transformer-0.1.2.dist-info/WHEEL
phynteny_transformer-0.1.2.dist-info/entry_points.txt
phynteny_transformer-0.1.2.dist-info/top_level.txt
phynteny_transformer-0.1.2.dist-info/zip-safe
phynteny_transformer-0.1.2.dist-info/RECORD
