Metadata-Version: 2.4
Name: phynteny_transformer
Version: 0.1.2
Summary: Phynteny: Synteny-based prediction of bacteriophage genes
Home-page: https://github.com/susiegriggo/Phynteny_transformer
Author: Susanna Grigson
Author-email: susie.grigson@gmail.com
License: MIT
Classifier: Development Status :: 1 - Planning
Classifier: Programming Language :: Python :: 3
Classifier: License :: OSI Approved :: MIT License
Classifier: Natural Language :: English
Classifier: Topic :: Scientific/Engineering :: Bio-Informatics
Classifier: Operating System :: OS Independent
Requires-Python: >=3.8
License-File: LICENSE
Requires-Dist: loguru
Requires-Dist: click
Requires-Dist: torch>=2.0.0
Requires-Dist: numpy
Requires-Dist: biopython
Requires-Dist: scikit-learn
Requires-Dist: transformers
Requires-Dist: pandas
Requires-Dist: tqdm
Dynamic: author
Dynamic: author-email
Dynamic: classifier
Dynamic: description
Dynamic: description-content-type
Dynamic: home-page
Dynamic: license
Dynamic: license-file
Dynamic: requires-dist
Dynamic: requires-python
Dynamic: summary
